myparsers/__init__.py
myparsers/readlinux.py
myparsers-0.1.dist-info/METADATA
myparsers-0.1.dist-info/WHEEL
myparsers-0.1.dist-info/top_level.txt
myparsers-0.1.dist-info/RECORD
