Metadata-Version: 2.1
Name: myparsers
Version: 0.1
Summary: A collection of file parsing functions
Requires-Python: >=3.10
